{
  "dossier_id": "DOS-034",
  "full_name": "Georgina Ruby Guerra",
  "national_id": "Eg538975qT",
  "date_of_birth": "1985-12-22",
  "email": "orozcopatricio@example.org",
  "phone": "392-873-8978",
  "address": "Privada Djibouti 051 Edif. 756 , Depto. 498, Vieja Tuvalu, SIN 38595",
  "employment_status": "self_employed",
  "employer": "Chacón, Saldaña y Anaya",
  "declared_monthly_income_usd": 9820.21,
  "credit_requested_usd": 76454.8,
  "loan_purpose": "debt_consolidation",
  "years_at_current_job": 4,
  "existing_debts_usd": 8504.36
}